README.txt
setup.py
DOMinclude.egg-info/PKG-INFO
DOMinclude.egg-info/SOURCES.txt
DOMinclude.egg-info/dependency_links.txt
DOMinclude.egg-info/entry_points.txt
DOMinclude.egg-info/not-zip-safe
DOMinclude.egg-info/paster_plugins.txt
DOMinclude.egg-info/requires.txt
DOMinclude.egg-info/top_level.txt
dominclude/__init__.py
dominclude/release.py
dominclude/widgets.py
dominclude/static/css/DOMinclude.css
dominclude/static/images/favicon.ico
dominclude/static/images/indicator_snake.gif
dominclude/static/images/tg_under_the_hood.png
dominclude/static/javascript/DOMinclude.js
dominclude/static/javascript/DOMinclude_config.js
dominclude/templates/__init__.py
dominclude/tests/__init__.py
dominclude/tests/test_dominclude.py
