Metadata-Version: 1.0
Name: DOMinclude
Version: 1.0.1
Summary: TurboGears widget that wraps the DOMinclude library for DOM-based popups.
Home-page: http://docs.turbogears.org/tgDOMinclude
Author: Christian Heilmann, Kevin Dangoor
Author-email: dangoor+dominclude@gmail.com
License: MIT
Download-URL: http://pypi.python.org/pypi/DOMinclude/
Keywords: turbogears.widgets
Platform: UNKNOWN
Classifier: Development Status :: 4 - Beta
Classifier: Operating System :: OS Independent
Classifier: Programming Language :: Python
Classifier: Topic :: Software Development :: Libraries :: Python Modules
Classifier: Framework :: TurboGears
Classifier: Framework :: TurboGears :: Widgets
